nonebot_plugin_bili_push_kook/__init__.py
nonebot_plugin_bili_push_kook-1.1.11.dist-info/LICENSE
nonebot_plugin_bili_push_kook-1.1.11.dist-info/METADATA
nonebot_plugin_bili_push_kook-1.1.11.dist-info/WHEEL
nonebot_plugin_bili_push_kook-1.1.11.dist-info/top_level.txt
nonebot_plugin_bili_push_kook-1.1.11.dist-info/RECORD
