Metadata-Version: 2.1
Name: nonebot-plugin-bili-push-kook
Version: 1.1.11
Summary: nonebot plugin bili push
Home-page: https://github.com/SuperGuGuGu/nonebot_plugin_bili_push
Author: SuperGuGuGu
Author-email: 13680478000@163.com
Requires-Python: >=3.8
License-File: LICENSE
Requires-Dist: pillow >=9.5.0
Requires-Dist: httpx >=0.24.1
Requires-Dist: requests >=2.31.0
Requires-Dist: toml >=0.10.2
Requires-Dist: nonebot2 >=2.0.0
Requires-Dist: nonebot-adapter-kaiheila >=0.2.12
Requires-Dist: nonebot-plugin-apscheduler >=0.2.0
